.DS_Store
meanderpy/__init__.py
meanderpy/code_for_getting_cutoff_dists_in_meanedrpy_3d_models.py
meanderpy/meanderpy.py
meanderpy-0.1.9.dist-info/LICENSE.txt
meanderpy-0.1.9.dist-info/METADATA
meanderpy-0.1.9.dist-info/WHEEL
meanderpy-0.1.9.dist-info/top_level.txt
meanderpy-0.1.9.dist-info/RECORD
