Metadata-Version: 2.1
Name: meanderpy
Version: 0.1.9
Summary: meanderpy: a simple model of meandering
Home-page: https://github.com/zsylvester/meanderpy
Author: Zoltan Sylvester
Author-email: zoltan.sylvester@beg.utexas.edu
License: UNKNOWN
Keywords: rivers,meandering,geomorphology,stratigraphy
Platform: UNKNOWN
Classifier: Programming Language :: Python :: 3
Classifier: Intended Audience :: Science/Research
Classifier: License :: OSI Approved :: Apache Software License
Classifier: Operating System :: OS Independent
License-File: LICENSE.txt
Requires-Dist: numpy
Requires-Dist: matplotlib
Requires-Dist: scipy
Requires-Dist: numba
Requires-Dist: pillow
Requires-Dist: scikit-image
Requires-Dist: tqdm
